{
    "swagger": "2.0",
    "info": {
        "contact": {}
    },
    "paths": {
        "/messages": {
            "get": {
                "produces": [
                    "application/json"
                ],
                "tags": [
                    "messages"
                ],
                "summary": "Get messages by status",
                "parameters": [
                    {
                        "enum": [
                            "UNSENT",
                            "SENT",
                            "REJECTED"
                        ],
                        "type": "string",
                        "description": "Filter by status",
                        "name": "status",
                        "in": "query"
                    }
                ],
                "responses": {
                    "200": {
                        "description": "OK",
                        "schema": {
                            "type": "array",
                            "items": {
                                "$ref": "#/definitions/github_com_SevcanDogramaci_message-sending-scheduler_internal_model.Message"
                            }
                        }
                    }
                }
            }
        },
        "/scheduler/start": {
            "post": {
                "tags": [
                    "scheduler"
                ],
                "summary": "Start scheduler",
                "responses": {
                    "200": {
                        "description": "OK"
                    }
                }
            }
        },
        "/scheduler/stop": {
            "post": {
                "tags": [
                    "scheduler"
                ],
                "summary": "Stop scheduler",
                "responses": {
                    "200": {
                        "description": "OK"
                    }
                }
            }
        }
    },
    "definitions": {
        "github_com_SevcanDogramaci_message-sending-scheduler_internal_model.Message": {
            "type": "object",
            "properties": {
                "content": {
                    "type": "string"
                },
                "id": {
                    "type": "string"
                },
                "recipient_phone_no": {
                    "type": "string"
                },
                "sender_phone_no": {
                    "type": "string"
                },
                "status": {
                    "$ref": "#/definitions/github_com_SevcanDogramaci_message-sending-scheduler_internal_model.Status"
                }
            }
        },
        "github_com_SevcanDogramaci_message-sending-scheduler_internal_model.Status": {
            "type": "string",
            "enum": [
                "UNSENT",
                "SENT",
                "REJECTED"
            ],
            "x-enum-varnames": [
                "StatusUnsent",
                "StatusSent",
                "StatusRejected"
            ]
        }
    }
}